mindsight_sampler-0.4.dist-info/METADATA
mindsight_sampler-0.4.dist-info/RECORD
mindsight_sampler-0.4.dist-info/WHEEL
mindsight_sampler-0.4.dist-info/top_level.txt
sampler/__init__.py
