Metadata-Version: 2.1
Name: mindsight-sampler
Version: 0.4
Summary: Mindsight Stack Sample Collector
Home-page: https://github.com/MindsightCo/python-sampler
Author: UNKNOWN
Author-email: UNKNOWN
License: Apache 2.0
Platform: UNKNOWN
Requires-Dist: requests
